JingtongNumpyShuzhiFenxiChuyiFix1/README.md
JingtongNumpyShuzhiFenxiChuyiFix1/__init__.py
JingtongNumpyShuzhiFenxiChuyiFix1/__main__.py
JingtongNumpyShuzhiFenxiChuyiFix1/file.epub
JingtongNumpyShuzhiFenxiChuyiFix1/index.html
JingtongNumpyShuzhiFenxiChuyiFix1/css/__init__.py
JingtongNumpyShuzhiFenxiChuyiFix1/css/annotations.css
JingtongNumpyShuzhiFenxiChuyiFix1/css/main.css
JingtongNumpyShuzhiFenxiChuyiFix1/css/normalize.css
JingtongNumpyShuzhiFenxiChuyiFix1/css/popup.css
JingtongNumpyShuzhiFenxiChuyiFix1/font/__init__.py
JingtongNumpyShuzhiFenxiChuyiFix1/font/fontello.eot
JingtongNumpyShuzhiFenxiChuyiFix1/font/fontello.svg
JingtongNumpyShuzhiFenxiChuyiFix1/font/fontello.ttf
JingtongNumpyShuzhiFenxiChuyiFix1/font/fontello.woff
JingtongNumpyShuzhiFenxiChuyiFix1/img/__init__.py
JingtongNumpyShuzhiFenxiChuyiFix1/img/annotator-glyph-sprite.png
JingtongNumpyShuzhiFenxiChuyiFix1/img/annotator-icon-sprite.png
JingtongNumpyShuzhiFenxiChuyiFix1/img/apple-touch-icon.png
JingtongNumpyShuzhiFenxiChuyiFix1/img/cancelfullscreen.png
JingtongNumpyShuzhiFenxiChuyiFix1/img/close.png
JingtongNumpyShuzhiFenxiChuyiFix1/img/fullscreen.png
JingtongNumpyShuzhiFenxiChuyiFix1/img/loader.gif
JingtongNumpyShuzhiFenxiChuyiFix1/img/menu-icon.png
JingtongNumpyShuzhiFenxiChuyiFix1/img/save.png
JingtongNumpyShuzhiFenxiChuyiFix1/img/saved.png
JingtongNumpyShuzhiFenxiChuyiFix1/img/settings-s.png
JingtongNumpyShuzhiFenxiChuyiFix1/img/settings.png
JingtongNumpyShuzhiFenxiChuyiFix1/img/star.png
JingtongNumpyShuzhiFenxiChuyiFix1/js/__init__.py
JingtongNumpyShuzhiFenxiChuyiFix1/js/epub.js
JingtongNumpyShuzhiFenxiChuyiFix1/js/epub.min.js
JingtongNumpyShuzhiFenxiChuyiFix1/js/epub.min.map
JingtongNumpyShuzhiFenxiChuyiFix1/js/hooks.min.js
JingtongNumpyShuzhiFenxiChuyiFix1/js/hooks.min.map
JingtongNumpyShuzhiFenxiChuyiFix1/js/reader.js
JingtongNumpyShuzhiFenxiChuyiFix1/js/reader.js.map
JingtongNumpyShuzhiFenxiChuyiFix1/js/reader.min.js
JingtongNumpyShuzhiFenxiChuyiFix1/js/reader.min.map
jingtong_numpy_shuzhi_fenxi_chuyi_fix1-2025.3.24.0.dist-info/METADATA
jingtong_numpy_shuzhi_fenxi_chuyi_fix1-2025.3.24.0.dist-info/WHEEL
jingtong_numpy_shuzhi_fenxi_chuyi_fix1-2025.3.24.0.dist-info/entry_points.txt
jingtong_numpy_shuzhi_fenxi_chuyi_fix1-2025.3.24.0.dist-info/top_level.txt
jingtong_numpy_shuzhi_fenxi_chuyi_fix1-2025.3.24.0.dist-info/RECORD
